deepmodel/__init__.py
deepmodel/data.py
deepmodel/param.py
deepmodel/utils.py
deepmodel/core/__init__.py
deepmodel/core/activation.py
deepmodel/core/layers.py
deepmodel/core/sequence.py
deepmodel/models/__init__.py
deepmodel/models/deepfm.py
deepmodel/models/din.py
deepmodel/models/mmvt.py
deepmodel/models/youtube.py
deepmodel/utils/__init__.py
deepmodel/utils/loss.py
deepmodel/utils/metric.py
deepmodel/utils/mysql.py
deepmodel/utils/tools.py
deepModel-0.1.0.dist-info/METADATA
deepModel-0.1.0.dist-info/WHEEL
deepModel-0.1.0.dist-info/top_level.txt
deepModel-0.1.0.dist-info/RECORD
